mkdocs_thebe/__init__.py
mkdocs_thebe/plugin.py
mkdocs_thebe/assets/__init__.py
mkdocs_thebe/assets/main.html
mkdocs_thebe/assets/mkdocs-thebe.css
mkdocs_thebe/assets/mkdocs-thebe.js
mkdocs_thebe-0.1.0.dist-info/LICENSE
mkdocs_thebe-0.1.0.dist-info/METADATA
mkdocs_thebe-0.1.0.dist-info/WHEEL
mkdocs_thebe-0.1.0.dist-info/entry_points.txt
mkdocs_thebe-0.1.0.dist-info/top_level.txt
mkdocs_thebe-0.1.0.dist-info/RECORD
