Metadata-Version: 2.1
Name: mkdocs-thebe
Version: 0.1.0
License-File: LICENSE
Provides-Extra: dev
Requires-Dist: pytest ; extra == 'dev'
Requires-Dist: flake8 ; extra == 'dev'
Requires-Dist: invoke ; extra == 'dev'
Requires-Dist: twine ; extra == 'dev'
